[
  {
    "discordID": "121630407782432769",
    "name": "womack",
    "sigma": 1.618,
    "mu": 25,
    "wins": 0,
    "losses": 0,
    "region": "EU"
  },
  {
    "discordID": "245173261254656001",
    "name": "Rutha",
    "sigma": 1.618,
    "mu": 25,
    "wins": 0,
    "losses": 0,
    "region": "EU"
  },
  {
    "discordID": "131427020369297408",
    "name": "vAgue",
    "sigma": 1.618,
    "mu": 25,
    "wins": 0,
    "losses": 0,
    "region": "EU"
  },
  {
    "discordID": "139459892653064193",
    "name": "bewz",
    "sigma": 1.618,
    "mu": 25,
    "wins": 0,
    "losses": 0,
    "region": "EU"
  },
  {
    "discordID": "150933458414206976",
    "name": "Joltz",
    "sigma": 1.618,
    "mu": 25,
    "wins": 0,
    "losses": 0,
    "region": "EU"
  },
  {
    "discordID": "211816250819477504",
    "name": "Furic",
    "sigma": 1.618,
    "mu": 25,
    "wins": 0,
    "losses": 0,
    "region": "EU"
  },
  {
    "discordID": "105359026811846656",
    "name": "randler#7453",
    "sigma": 1.618,
    "mu": 25,
    "wins": 0,
    "losses": 0,
    "region": "EU"
  },
  {
    "discordID": "85306030287773696",
    "name": "Godof",
    "sigma": 1.618,
    "mu": 25,
    "wins": 0,
    "losses": 0,
    "region": "EU"
  },
  {
    "discordID": "227069702461980674",
    "name": "Srymea",
    "sigma": 1.618,
    "mu": 25,
    "wins": 0,
    "losses": 0,
    "region": "EU"
  },
  {
    "discordID": "83555170096517120",
    "name": "Synoo",
    "sigma": 1.618,
    "mu": 25,
    "wins": 0,
    "losses": 0,
    "region": "EU"
  },
  {
    "discordID": "329143148511232010",
    "name": "TheMostCommonBoy",
    "sigma": 1.618,
    "mu": 25,
    "wins": 0,
    "losses": 0,
    "region": "EU"
  },
  {
    "discordID": "141175772588146688",
    "name": "klerny",
    "sigma": 1.618,
    "mu": 25,
    "wins": 0,
    "losses": 0,
    "region": "EU"
  },
  {
    "discordID": "126816150314156043",
    "name": "mr2",
    "sigma": 1.618,
    "mu": 25,
    "wins": 0,
    "losses": 0,
    "region": "EU"
  },
  {
    "discordID": "196737766770343937",
    "name": "Hotbiscuit",
    "sigma": 1.618,
    "mu": 25,
    "wins": 0,
    "losses": 0,
    "region": "EU"
  },
  {
    "discordID": "246637371234320386",
    "name": "MORVWY",
    "sigma": 1.618,
    "mu": 25,
    "wins": 0,
    "losses": 0,
    "region": "EU"
  },
  {
    "discordID": "194371096047255552",
    "name": "Lum1nary",
    "sigma": 1.618,
    "mu": 25,
    "wins": 0,
    "losses": 0,
    "region": "EU"
  },
  {
    "discordID": "249265019328528397",
    "name": "idol",
    "sigma": 1.618,
    "mu": 25,
    "wins": 0,
    "losses": 0,
    "region": "EU"
  },
  {
    "discordID": "209709911460806657",
    "name": "Xqkfuu",
    "sigma": 1.618,
    "mu": 25,
    "wins": 0,
    "losses": 0,
    "region": "EU"
  },
  {
    "discordID": "82968090089885696",
    "name": "Jeter",
    "sigma": 1.618,
    "mu": 25,
    "wins": 0,
    "losses": 0,
    "region": "EU"
  },
  {
    "discordID": "273204979257573376",
    "name": "Imoshen",
    "sigma": 1.618,
    "mu": 25,
    "wins": 0,
    "losses": 0,
    "region": "EU"
  },
  {
    "discordID": "119180619954520068",
    "name": "Dizzl3r",
    "sigma": 1.618,
    "mu": 25,
    "wins": 0,
    "losses": 0,
    "region": "EU"
  },
  {
    "discordID": "207582905684197377",
    "name": "Jurgen",
    "sigma": 1.618,
    "mu": 25,
    "wins": 0,
    "losses": 0,
    "region": "EU"
  },
  {
    "discordID": "170222708347371521",
    "name": "yy.",
    "sigma": 1.618,
    "mu": 25,
    "wins": 0,
    "losses": 0,
    "region": "EU"
  },
  {
    "discordID": "254612619997085697",
    "name": "gezab",
    "sigma": 1.618,
    "mu": 25,
    "wins": 0,
    "losses": 0,
    "region": "EU"
  },
  {
    "discordID": "137189843363954688",
    "name": "loreo",
    "sigma": 1.618,
    "mu": 25,
    "wins": 0,
    "losses": 0,
    "region": "EU"
  },
  {
    "discordID": "105221541024772096",
    "name": "Averse",
    "sigma": 1.618,
    "mu": 25,
    "wins": 0,
    "losses": 0,
    "region": "NA"
  },
  {
    "discordID": "150354957613268992",
    "name": "slsfknsucks",
    "sigma": 1.618,
    "mu": 25,
    "wins": 0,
    "losses": 0,
    "region": "EU"
  },
  {
    "discordID": "278991025278681099",
    "name": "GeekishNerd",
    "sigma": 1.618,
    "mu": 25,
    "wins": 0,
    "losses": 0,
    "region": "EU"
  },
  {
    "discordID": "159379649670021120",
    "name": "YourN1ghtmare-",
    "sigma": 1.618,
    "mu": 25,
    "wins": 0,
    "losses": 0,
    "region": "EU"
  },
  {
    "discordID": "146751963458043904",
    "name": "bbiceps-",
    "sigma": 1.618,
    "mu": 25,
    "wins": 0,
    "losses": 0,
    "region": "EU"
  },
  {
    "discordID": "286147583959891968",
    "name": "Nathlan",
    "sigma": 1.618,
    "mu": 25,
    "wins": 0,
    "losses": 0,
    "region": "EU"
  },
  {
    "discordID": "233347968378339328",
    "name": "Curlicue",
    "sigma": 1.618,
    "mu": 25,
    "wins": 0,
    "losses": 0,
    "region": "EU"
  },
  {
    "discordID": "222776093793320961",
    "name": "Larss",
    "sigma": 1.618,
    "mu": 25,
    "wins": 0,
    "losses": 0,
    "region": "EU"
  },
  {
    "discordID": "289816984718409728",
    "name": "fred",
    "sigma": 1.618,
    "mu": 25,
    "wins": 0,
    "losses": 0,
    "region": "EU"
  },
  {
    "discordID": "314521107270991873",
    "name": "VASIAGARAJ",
    "sigma": 1.618,
    "mu": 25,
    "wins": 0,
    "losses": 0,
    "region": "EU"
  },
  {
    "discordID": "272420080179216385",
    "name": "Nosomi",
    "sigma": 1.618,
    "mu": 25,
    "wins": 0,
    "losses": 0,
    "region": "EU"
  },
  {
    "discordID": "111554089896194048",
    "name": "tomiy",
    "sigma": 1.618,
    "mu": 25,
    "wins": 0,
    "losses": 0,
    "region": "EU"
  },
  {
    "discordID": "221024427456856064",
    "name": "eygrr",
    "sigma": 1.618,
    "mu": 25,
    "wins": 0,
    "losses": 0,
    "region": "EU"
  },
  {
    "discordID": "108605402383388672",
    "name": "mulkmulkmulk",
    "sigma": 1.618,
    "mu": 25,
    "wins": 0,
    "losses": 0,
    "region": "EU"
  },
  {
    "discordID": "295547494128156672",
    "name": "cha1x",
    "sigma": 1.618,
    "mu": 25,
    "wins": 0,
    "losses": 0,
    "region": "EU"
  },
  {
    "discordID": "175675112123662337",
    "name": "Antaresiq",
    "sigma": 1.618,
    "mu": 25,
    "wins": 0,
    "losses": 0,
    "region": "EU"
  },
  {
    "discordID": "82164084409114624",
    "name": "lokkut",
    "sigma": 1.618,
    "mu": 25,
    "wins": 0,
    "losses": 0,
    "region": "EU"
  },
  {
    "discordID": "230436820876263424",
    "name": "FarsanTS",
    "sigma": 1.618,
    "mu": 25,
    "wins": 0,
    "losses": 0,
    "region": "EU"
  },
  {
    "discordID": "154621742776582144",
    "name": "pimmo",
    "sigma": 1.618,
    "mu": 25,
    "wins": 0,
    "losses": 0,
    "region": "EU"
  }
]